jupyter_jsc_jupyterhub_customization/__init__.py
jupyter_jsc_jupyterhub_customization/misc.py
jupyter_jsc_jupyterhub_customization/apihandler/__init__.py
jupyter_jsc_jupyterhub_customization/apihandler/incidents.py
jupyter_jsc_jupyterhub_customization/apihandler/misc.py
jupyter_jsc_jupyterhub_customization/apihandler/notebook_template_server.py
jupyter_jsc_jupyterhub_customization/apihandler/refresh_hpc_accounts.py
jupyter_jsc_jupyterhub_customization/apihandler/self_api_handler_oauth.py
jupyter_jsc_jupyterhub_customization/apihandler/slurm_wrapper.py
jupyter_jsc_jupyterhub_customization/apihandler/tunnel_restart.py
jupyter_jsc_jupyterhub_customization/apihandler/twoFA.py
jupyter_jsc_jupyterhub_customization/apihandler/user_count.py
jupyter_jsc_jupyterhub_customization/apihandler/userjobs.py
jupyter_jsc_jupyterhub_customization/apihandler/utils/__init__.py
jupyter_jsc_jupyterhub_customization/apihandler/utils/twoFA_mail.py
jupyter_jsc_jupyterhub_customization/apihandler/utils/twoFA_orm.py
jupyter_jsc_jupyterhub_customization/apihandler/utils/twoFA_unity.py
jupyter_jsc_jupyterhub_customization/authenticator/__init__.py
jupyter_jsc_jupyterhub_customization/authenticator/api_services.py
jupyter_jsc_jupyterhub_customization/authenticator/oauthenticator.py
jupyter_jsc_jupyterhub_customization/handler/__init__.py
jupyter_jsc_jupyterhub_customization/handler/page_handlers.py
jupyter_jsc_jupyterhub_customization/logs/__init__.py
jupyter_jsc_jupyterhub_customization/logs/extra_handlers.py
jupyter_jsc_jupyterhub_customization/logs/loglevel.py
jupyter_jsc_jupyterhub_customization/logs/utils.py
jupyter_jsc_jupyterhub_customization/spawner/__init__.py
jupyter_jsc_jupyterhub_customization/spawner/api_options_form.py
jupyter_jsc_jupyterhub_customization/spawner/api_setup_tunnel.py
jupyter_jsc_jupyterhub_customization/spawner/api_spawn_notification_sse.py
jupyter_jsc_jupyterhub_customization/spawner/api_spawn_options_update.py
jupyter_jsc_jupyterhub_customization-4.0.0.1.dist-info/LICENSE
jupyter_jsc_jupyterhub_customization-4.0.0.1.dist-info/METADATA
jupyter_jsc_jupyterhub_customization-4.0.0.1.dist-info/WHEEL
jupyter_jsc_jupyterhub_customization-4.0.0.1.dist-info/top_level.txt
jupyter_jsc_jupyterhub_customization-4.0.0.1.dist-info/RECORD
